{
    "Ar36": {
        "error": 0.0007947775092923733,
        "error_type": "SEM",
        "filter_outliers_dict": {
            "filter_outliers": true,
            "iterations": 2,
            "std_devs": 2
        },
        "fit": "Parabolic",
        "value": 0.0876869657496686
    },
    "Ar37": {
        "error": 0.016102368673422098,
        "error_type": "SEM",
        "filter_outliers_dict": {
            "filter_outliers": true,
            "iterations": 2,
            "std_devs": 2
        },
        "fit": "linear",
        "value": 51.648831868299766
    },
    "Ar38": {
        "error": 0.00470743600056903,
        "error_type": "SEM",
        "filter_outliers_dict": {
            "filter_outliers": true,
            "iterations": 2,
            "std_devs": 2
        },
        "fit": "linear",
        "value": 0.4863148208915143
    },
    "Ar39": {
        "error": 0.013522814431744546,
        "error_type": "SEM",
        "filter_outliers_dict": {
            "filter_outliers": true,
            "iterations": 2,
            "std_devs": 2
        },
        "fit": "Parabolic",
        "value": 7.108418067842894
    },
    "Ar40": {
        "error": 0.059181381084598764,
        "error_type": "SEM",
        "filter_outliers_dict": {
            "filter_outliers": true,
            "iterations": 2,
            "std_devs": 2
        },
        "fit": "Parabolic",
        "value": 331.3971254826828
    }
}