{
    "Ar36": {
        "error": 0.0005259055066262733,
        "error_type": "SEM",
        "filter_outliers_dict": {
            "filter_outliers": true,
            "iterations": 2,
            "std_devs": 2
        },
        "fit": "Parabolic",
        "value": 0.047528127421390204
    },
    "Ar37": {
        "error": 0.01581515127072172,
        "error_type": "SEM",
        "filter_outliers_dict": {
            "filter_outliers": true,
            "iterations": 1,
            "std_devs": 3,
            "use_iqr_filtering": false,
            "use_standard_deviation_filtering": false
        },
        "fit": "linear",
        "fn": 338,
        "include_baseline_error": true,
        "n": 340,
        "outlier_excluded": [
            262,
            270
        ],
        "reviewed": true,
        "user_excluded": [],
        "value": 0.31328605922046604
    },
    "Ar38": {
        "error": 0.0053073844859105905,
        "error_type": "SEM",
        "filter_outliers_dict": {
            "filter_outliers": true,
            "iterations": 1,
            "std_devs": 3,
            "use_iqr_filtering": false,
            "use_standard_deviation_filtering": false
        },
        "fit": "linear",
        "fn": 339,
        "include_baseline_error": true,
        "n": 340,
        "outlier_excluded": [
            218
        ],
        "reviewed": true,
        "user_excluded": [],
        "value": 0.17435898256409546
    },
    "Ar39": {
        "error": 0.008042015287140549,
        "error_type": "SEM",
        "filter_outliers_dict": {
            "filter_outliers": true,
            "iterations": 1,
            "std_devs": 3,
            "use_iqr_filtering": false,
            "use_standard_deviation_filtering": false
        },
        "fit": "linear",
        "fn": 338,
        "include_baseline_error": true,
        "n": 340,
        "outlier_excluded": [
            225,
            100
        ],
        "reviewed": true,
        "user_excluded": [],
        "value": 3.7436383777508353
    },
    "Ar40": {
        "error": 0.03189221184540706,
        "error_type": "SEM",
        "filter_outliers_dict": {
            "filter_outliers": true,
            "iterations": 1,
            "std_devs": 3,
            "use_iqr_filtering": false,
            "use_standard_deviation_filtering": false
        },
        "fit": "parabolic",
        "fn": 339,
        "include_baseline_error": true,
        "n": 340,
        "outlier_excluded": [
            236
        ],
        "reviewed": true,
        "user_excluded": [],
        "value": 54.18490224602698
    }
}